observer_ollama/__init__.py
observer_ollama/__main__.py
observer_ollama/command_executor.py
observer_ollama/cors.py
observer_ollama/handler.py
observer_ollama/network_helper.py
observer_ollama/ollama_client.py
observer_ollama/server.py
observer_ollama/ssl_helper.py
observer_ollama/translator.py
observer_ollama-0.2.2.dist-info/licenses/LICENSE
observer_ollama-0.2.2.dist-info/METADATA
observer_ollama-0.2.2.dist-info/WHEEL
observer_ollama-0.2.2.dist-info/entry_points.txt
observer_ollama-0.2.2.dist-info/top_level.txt
observer_ollama-0.2.2.dist-info/RECORD
