Metadata-Version: 2.4
Name: observer-ollama
Version: 0.2.2
Summary: HTTPS proxy with CORS support for Ollama
Author-email: Roy Medina <roymedina@me.com>
License: MIT License
Classifier: Programming Language :: Python :: 3
Classifier: License :: OSI Approved :: MIT License
Classifier: Operating System :: OS Independent
Requires-Python: >=3.10
License-File: LICENSE
Dynamic: license-file
